{
  "$schema": "https://ui.shadcn.com/schema/registry.json",
  "name": "acme",
  "homepage": "https://ui.ahmet.studio",
  "items": [
    {
      "name": "dual-sidebar",
      "type": "registry:component",
      "title": "Dual Sidebar",
      "description": "A dual sidebar component",
      "registryDependencies": ["button", "input", "separator", "sheet", "skeleton", "tooltip", "use-mobile"],
      "files": [
        {
          "path": "registry/new-york/ui/dual-sidebar.tsx",
          "type": "registry:component"
        }
      ]
    }
  ]
}
